CHANGELOG.md
LICENSE
MANIFEST.in
README.md
setup.py
.pytest_cache/README.md
coolmessages/__init__.py
coolmessages/main.py
coolmessages/test_main.py
coolmessages.egg-info/PKG-INFO
coolmessages.egg-info/SOURCES.txt
coolmessages.egg-info/dependency_links.txt
coolmessages.egg-info/top_level.txt
coolmessages/characters/__init__.py
coolmessages/characters/all_characters.py
coolmessages/characters/animals.py
coolmessages/characters/cartoon.py
coolmessages/characters/games.py
coolmessages/characters/memes.py
docs/conf.py
venv/Lib/site-packages/imagesize.py
venv/Lib/site-packages/six.py
venv/Lib/site-packages/zipp.py
venv/Lib/site-packages/_distutils_hack/__init__.py
venv/Lib/site-packages/_distutils_hack/override.py
venv/Lib/site-packages/_pytest/__init__.py
venv/Lib/site-packages/_pytest/_argcomplete.py
venv/Lib/site-packages/_pytest/_version.py
venv/Lib/site-packages/_pytest/cacheprovider.py
venv/Lib/site-packages/_pytest/capture.py
venv/Lib/site-packages/_pytest/compat.py
venv/Lib/site-packages/_pytest/debugging.py
venv/Lib/site-packages/_pytest/deprecated.py
venv/Lib/site-packages/_pytest/doctest.py
venv/Lib/site-packages/_pytest/faulthandler.py
venv/Lib/site-packages/_pytest/fixtures.py
venv/Lib/site-packages/_pytest/freeze_support.py
venv/Lib/site-packages/_pytest/helpconfig.py
venv/Lib/site-packages/_pytest/hookspec.py
venv/Lib/site-packages/_pytest/junitxml.py
venv/Lib/site-packages/_pytest/legacypath.py
venv/Lib/site-packages/_pytest/logging.py
venv/Lib/site-packages/_pytest/main.py
venv/Lib/site-packages/_pytest/monkeypatch.py
venv/Lib/site-packages/_pytest/nodes.py
venv/Lib/site-packages/_pytest/nose.py
venv/Lib/site-packages/_pytest/outcomes.py
venv/Lib/site-packages/_pytest/pastebin.py
venv/Lib/site-packages/_pytest/pathlib.py
venv/Lib/site-packages/_pytest/pytester.py
venv/Lib/site-packages/_pytest/pytester_assertions.py
venv/Lib/site-packages/_pytest/python.py
venv/Lib/site-packages/_pytest/python_api.py
venv/Lib/site-packages/_pytest/python_path.py
venv/Lib/site-packages/_pytest/recwarn.py
venv/Lib/site-packages/_pytest/reports.py
venv/Lib/site-packages/_pytest/runner.py
venv/Lib/site-packages/idna-3.3.dist-info/LICENSE.md
