Metadata-Version: 2.1
Name: coolmessages
Version: 0.0.2
Summary: Enhance your terminal with cool and unnecessary messages 😏
Home-page: https://github.com/anonymouscoolguy/coolmessages
Author: anonymouscoolguy
Author-email: anonymouscoolguy69@gmail.com
License: MIT
Keywords: cool messages,terminal,terminal messages,ascii,ascii messages
Platform: UNKNOWN
Classifier: Development Status :: 3 - Alpha
Classifier: Intended Audience :: Developers
Classifier: License :: OSI Approved :: MIT License
Classifier: Programming Language :: Python :: 3
